starch/__init__.py
starch/config.py
starch/constants.py
starch/formatter.py
starch-0.1.0a10.dist-info/METADATA
starch-0.1.0a10.dist-info/WHEEL
starch-0.1.0a10.dist-info/entry_points.txt
starch-0.1.0a10.dist-info/licenses/LICENSE
starch-0.1.0a10.dist-info/RECORD
