Metadata-Version: 2.4
Name: starch
Version: 0.1.0a10
Dynamic: Author
Dynamic: Author-email
Summary: A configurable line-formatter for visually distinguishing comments.
License-Expression: MIT
License-File: LICENSE
Requires-Python: >=3.10
Requires-Dist: click>=8.2.1
Requires-Dist: platformdirs>=4.3.8
